mvinstall/__init__.py
mvinstall/__main__.py
mvinstall/s3install.py
mvinstall-0.3.0.dist-info/METADATA
mvinstall-0.3.0.dist-info/WHEEL
mvinstall-0.3.0.dist-info/entry_points.txt
mvinstall-0.3.0.dist-info/top_level.txt
mvinstall-0.3.0.dist-info/zip-safe
mvinstall-0.3.0.dist-info/RECORD
