Metadata-Version: 2.1
Name: mvinstall
Version: 0.3.0
Summary: mvinstall - install data and packages from S3.
Home-page: https://github.com/movandi
Author: Movandi
Author-email: 
License: Proprietary License
Keywords: deployment
Platform: any
Classifier: Development Status :: 4 - Beta
Classifier: Intended Audience :: Developers
Classifier: License :: Other/Proprietary License
Classifier: Operating System :: MacOS :: MacOS X
Classifier: Operating System :: Microsoft :: Windows
Classifier: Operating System :: POSIX
Classifier: Programming Language :: Python
Classifier: Programming Language :: Python :: 3.5
Classifier: Programming Language :: Python :: 3.6
Classifier: Programming Language :: Python :: 3.7
Provides: mvinstall
Requires-Python: >=3.5
Requires-Dist: minio
